README
htable.py
setup.py
htable.egg-info/PKG-INFO
htable.egg-info/SOURCES.txt
htable.egg-info/dependency_links.txt
htable.egg-info/requires.txt
htable.egg-info/top_level.txt