Metadata-Version: 1.1
Name: htable
Version: 0.1.1
Summary: Table-like formats to latex \table[H]
Home-page: https://github.com/cdown/htable
Author: Chris Down
Author-email: chris@chrisdown.name
License: Public Domain
Platform: UNKNOWN
Classifier: License :: Public Domain
Classifier: Programming Language :: Python :: 3
